multi_factor_model/__init__.py
multi_factor_model/cprint.py
multi_factor_model/evaluate.py
multi_factor_model/fit_model.py
multi_factor_model/prepare.py
multi_factor_model/utilise.py
multi_factor_model-0.0.0a5.dist-info/DESCRIPTION.rst
multi_factor_model-0.0.0a5.dist-info/METADATA
multi_factor_model-0.0.0a5.dist-info/RECORD
multi_factor_model-0.0.0a5.dist-info/WHEEL
multi_factor_model-0.0.0a5.dist-info/metadata.json
multi_factor_model-0.0.0a5.dist-info/top_level.txt
