Metadata-Version: 2.0
Name: multi-factor-model
Version: 0.0.0a5
Summary: factor model
Home-page: UNKNOWN
Author: Yili Peng
Author-email: yili_peng@outlook.com
License: UNKNOWN
Platform: UNKNOWN
